plover_windows_brightness.py
plover_windows_brightness-0.0.2.dist-info/DESCRIPTION.rst
plover_windows_brightness-0.0.2.dist-info/METADATA
plover_windows_brightness-0.0.2.dist-info/RECORD
plover_windows_brightness-0.0.2.dist-info/WHEEL
plover_windows_brightness-0.0.2.dist-info/entry_points.txt
plover_windows_brightness-0.0.2.dist-info/metadata.json
plover_windows_brightness-0.0.2.dist-info/top_level.txt
plover_windows_brightness-0.0.2.dist-info/zip-safe
